{
    "status": "Ok",
    "message": "Users list found",
    "users": [
        {
            "id": 1,
            "name": "Usman",
            "age": 25,
            "gender": "Male"
        },
        {
            "id": 2,
            "name": "Abdul",
            "age": 33,
            "gender": "Male"
        },
        {
            "id": 3,
            "name": "Usama",
            "age": 26,
            "gender": "Male"
        },
        {
            "id": 4,
            "name": "Haida G",
            "age": 24,
            "gender": "Female"
        },
        {
            "id": 5,
            "name": "Ali Raza",
            "age": 39,
            "gender": "Male"
        },
        {
            "id": 6,
            "name": "Eman",
            "age": 21,
            "gender": "Female"
        },
        {
            "id": 7,
            "name": "Yasir",
            "age": 29,
            "gender": "Male"
        },
        {
            "id": 8,
            "name": "Nasir",
            "age": 43,
            "gender": "Male"
        },
        {
            "id": 9,
            "name": "Nida",
            "age": 17,
            "gender": "Female"
        },
        {
            "id": 10,
            "name": "Hamza",
            "age": 20,
            "gender": "Male"
        }
    ]
}